freshdesk/__init__.py
freshdesk/api.py
freshdesk/v1/__init__.py
freshdesk/v1/api.py
freshdesk/v1/models.py
freshdesk/v1/tests/__init__.py
freshdesk/v1/tests/conftest.py
freshdesk/v1/tests/test_agent.py
freshdesk/v1/tests/test_api_class.py
freshdesk/v1/tests/test_comment.py
freshdesk/v1/tests/test_contact.py
freshdesk/v1/tests/test_customer.py
freshdesk/v1/tests/test_ticket.py
freshdesk/v1/tests/test_timesheets.py
freshdesk/v2/__init__.py
freshdesk/v2/api.py
freshdesk/v2/errors.py
freshdesk/v2/models.py
freshdesk/v2/tests/__init__.py
freshdesk/v2/tests/conftest.py
freshdesk/v2/tests/test_agent.py
freshdesk/v2/tests/test_api_class.py
freshdesk/v2/tests/test_comment.py
freshdesk/v2/tests/test_company.py
freshdesk/v2/tests/test_contact.py
freshdesk/v2/tests/test_customer.py
freshdesk/v2/tests/test_group.py
freshdesk/v2/tests/test_role.py
freshdesk/v2/tests/test_solutions.py
freshdesk/v2/tests/test_ticket.py
freshdesk/v2/tests/test_time_entry.py
python_freshdesk-1.3.9.dist-info/LICENSE
python_freshdesk-1.3.9.dist-info/METADATA
python_freshdesk-1.3.9.dist-info/WHEEL
python_freshdesk-1.3.9.dist-info/top_level.txt
python_freshdesk-1.3.9.dist-info/RECORD
