Metadata-Version: 2.1
Name: python-freshdesk
Version: 1.3.9
Summary: An API for the Freshdesk helpdesk
Home-page: https://github.com/sjkingo/python-freshdesk
Author: Sam Kingston
Author-email: sam@sjkwi.com.au
License: BSD
Platform: UNKNOWN
License-File: LICENSE
Requires-Dist: requests
Requires-Dist: python-dateutil
